pycarot/__init__.py
pycarot/__main__.py
pycarot/event.py
pycarot/progress.py
pycarot/ioc/__init__.py
pycarot/ioc/container.py
pycarot/ioc/entries.py
pycarot/ioc/exceptions.py
pycarot/ioc/static.py
tests/__init__.py
tests/test_event.py
pycarot-0.0.4.dist-info/LICENSE
pycarot-0.0.4.dist-info/METADATA
pycarot-0.0.4.dist-info/WHEEL
pycarot-0.0.4.dist-info/entry_points.txt
pycarot-0.0.4.dist-info/top_level.txt
pycarot-0.0.4.dist-info/RECORD
